{
      "title": "TOP 5 EVENT SOURCES",
      "visState": "{\n  \"aggs\": [\n    {\n      \"id\": \"1\",\n      \"params\": {},\n      \"schema\": \"metric\",\n      \"type\": \"count\"\n    },\n    {\n      \"id\": \"2\",\n      \"params\": {\n        \"customLabel\": \"Event Sources\",\n        \"field\": \"module.keyword\",\n        \"order\": \"desc\",\n        \"orderBy\": \"1\",\n        \"size\": 5\n      },\n      \"schema\": \"segment\",\n      \"type\": \"terms\"\n    }\n  ],\n  \"listeners\": {},\n  \"params\": {\n    \"addLegend\": true,\n    \"addTooltip\": true,\n    \"isDonut\": false,\n    \"shareYAxis\": true\n  },\n  \"title\": \"Top 5 Event Sources (Pie Chart)\",\n  \"type\": \"pie\"\n}",
      "uiStateJSON": "{}",
      "description": "",
      "version": 1,
      "kibanaSavedObjectMeta": {
        "searchSourceJSON": "{\n  \"index\": \"logstash-*\",\n  \"filter\": [],\n  \"query\": {\n    \"query_string\": {\n      \"query\": \"*\",\n      \"analyze_wildcard\": true\n    }\n  },\n  \"highlight\": {\n    \"pre_tags\": [\n      \"@kibana-highlighted-field@\"\n    ],\n    \"post_tags\": [\n      \"@/kibana-highlighted-field@\"\n    ],\n    \"fields\": {\n      \"*\": {}\n    },\n    \"require_field_match\": false,\n    \"fragment_size\": 2147483647\n  }\n}"
      }
    }
